toolbox/__init__.py
toolbox/analytics.py
toolbox/db.py
toolbox/installed_mcp.py
toolbox/installer.py
toolbox/launchd.py
toolbox/settings.py
toolbox/setup.py
toolbox/toolbox_requirements.py
toolbox/user_utils.py
toolbox/cli/__init__.py
toolbox/cli/cli.py
toolbox/cli/daemon_cli.py
toolbox/cli/event_cli.py
toolbox/cli/trigger_cli.py
toolbox/daemon/__init__.py
toolbox/daemon/app.py
toolbox/daemon/daemon.py
toolbox/daemon/daemon_logging.py
toolbox/daemon/dependencies.py
toolbox/external_dependencies/__init__.py
toolbox/external_dependencies/external_depenencies.py
toolbox/mcp_clients/mcp_clients.py
toolbox/mcp_installer/__init__.py
toolbox/mcp_installer/mcp_installer.py
toolbox/mcp_installer/python_package_installer.py
toolbox/mcp_installer/uv_utils.py
toolbox/store/__init__.py
toolbox/store/installation_context.py
toolbox/store/store_code.py
toolbox/store/store_json.py
toolbox/store/callbacks/__init__.py
toolbox/store/callbacks/callback.py
toolbox/store/callbacks/pdf_callback.py
toolbox/store/callbacks/whatsapp_callback.py
toolbox/store/callbacks/auth/auth_discord_callback.py
toolbox/store/callbacks/auth/auth_slack.py
toolbox/store/callbacks/auth/auth_slack_browser_cookie_files.py
toolbox/store/callbacks/auth/auth_slack_callback.py
toolbox/store/callbacks/auth/auth_slack_keyring.py
toolbox/triggers/__init__.py
toolbox/triggers/cron_utils.py
toolbox/triggers/models.py
toolbox/triggers/scheduler.py
toolbox/triggers/trigger_store.py
toolbox/triggers/trigger_utils.py
toolbox/utils/__init__.py
toolbox/utils/healthcheck.py
toolbox/utils/utils.py
syft_toolbox-0.3.1.dist-info/METADATA
syft_toolbox-0.3.1.dist-info/WHEEL
syft_toolbox-0.3.1.dist-info/entry_points.txt
syft_toolbox-0.3.1.dist-info/RECORD
