Metadata-Version: 2.4
Name: syft_toolbox
Version: 0.3.1
Summary: Add your description here
Requires-Python: >=3.12
Requires-Dist: anthropic>=0.52.2
Requires-Dist: croniter>=6.0.0
Requires-Dist: fastapi[standard]>=0.116.1
Requires-Dist: leveldb-312==1.0.0
Requires-Dist: loguru>=0.7.3
Requires-Dist: mcp>=1.9.2
Requires-Dist: numpy>=2.3.2
Requires-Dist: playwright>=1.53.0
Requires-Dist: posthog>=6.5.0
Requires-Dist: psutil>=7.0.0
Requires-Dist: pycookiecheat
Requires-Dist: requests>=2.32.4
Requires-Dist: slack-sdk>=3.35.0
Requires-Dist: sqlalchemy>=2.0.42
Requires-Dist: sqlite-vec==0.1.7a2
Requires-Dist: tabulate>=0.9.0
Requires-Dist: typer>=0.16.0
Requires-Dist: uvicorn>=0.34.3
